{
    "Relevancy": [
        "Relevant"
    ],
    "New Records": [],
    "Key Match Events": [
        "WICKET! Australia 118-2 (Short c Smith b Potts 54)",
        "WICKET! Australia 78-1 (Head c Salt b Carse 31)",
        "WICKET! Rashid c Labuschagne b Head 36 (England 309 all out)",
        "WICKET! Potts c Inglis b Maxwell 6 (England 276-9)"
    ],
    "Pre-Game Insights": [],
    "Post-Match Reflections": [],
    "Miscellaneous Highlights": [
        "Rain stops play"
    ],
    "Others": [
        "England collapsed after a spectacular start with the bat as Australia won the ODI series decider on a rainy day in Bristol"
    ]
}