{
    "Relevancy": [
        "Relevant"
    ],
    "New Records": [],
    "Key Match Events": [
        "England scored 309/10 in 49.2 overs",
        "Australia scored 165/2 in 20.4 overs",
        "Travis Head was named Player of the Match and Player of the Series"
    ],
    "Pre-Game Insights": [],
    "Post-Match Reflections": [
        "Harry Brook named Player of the Summer for England",
        "Mitchell Marsh, Travis Head, and Harry Brook shared their thoughts on the series"
    ],
    "Miscellaneous Highlights": [
        "The match was reduced to 20 overs per side due to rain"
    ],
    "Others": []
}