{
    "Relevancy": [
        "Relevant"
    ],
    "New Records": [],
    "Key Match Events": [
        "Jamal Musiala scored a goal, assisted by Florian Wirtz (Germany's second goal)",
        "Florian Wirtz scored a goal, assisted by Jamal Musiala (Germany's third goal)",
        "Kevin Csoboth had 1 shot on goal (Hungary)"
    ],
    "Pre-Game Insights": [],
    "Post-Match Reflections": [
        "No post-match reflections provided in the article"
    ],
    "Miscellaneous Highlights": [
        "The match took place at Merkur Spiel-Arena, Dusseldorf, DEU"
    ],
    "Others": []
}