{
    "Relevancy": [
        "Relevant"
    ],
    "New Records": [],
    "Key Match Events": [
        "The match between Australia and England was washed out due to rain, resulting in shared points for both teams."
    ],
    "Pre-Game Insights": [
        "Australia and England are vulnerable in the T20 World Cup after the washout, with their chances of qualifying for the semifinals affected by the result."
    ],
    "Post-Match Reflections": [],
    "Miscellaneous Highlights": [
        "The shared points mean that all teams in Group 1 can still qualify for the semifinals."
    ],
    "Others": [
        "The Net Run Rate (NRR) is a crucial factor in determining the teams' chances of qualifying, with New Zealand having a significant edge in this department."
    ]
}