{
    "Relevancy": [
        "Irrelevant"
    ],
    "New Records": [],
    "Key Match Events": [],
    "Pre-Game Insights": [],
    "Post-Match Reflections": [],
    "Miscellaneous Highlights": [
        "The game of dominoes also is ingrained in Latin American culture. Family get-togethers and hangouts can last all night playing."
    ],
    "Others": [
        "The Marlins play by the Dominican Republic rules, starting with the double six tile.",
        "If the same people are competing, whoever won the last round starts things off.",
        "During pregame, the loser has to drink a half bottle of water. Postgame, it’s 10 pushups.",
        "Dominoes is serious business, so much so Alcantara went directly to the table following his 35-pitch bullpen while still clad in his blue alternate jersey."
    ]
}