{
    "Relevancy": [
        "Relevant"
    ],
    "New Records": [
        "Jos Buttler scored 73 runs off 47 balls, a significant individual performance"
    ],
    "Key Match Events": [
        "England secured a 20-run victory over New Zealand",
        "Multiple key wickets fell in New Zealand's chase, including Kane Williamson and Devon Conway",
        "England's spinners and fast bowlers played crucial roles in containing New Zealand's scoring"
    ],
    "Pre-Game Insights": [
        "England won the toss and chose to bat first"
    ],
    "Post-Match Reflections": [
        "England's win kept their tournament hopes alive",
        "Jos Buttler was named Player of the Match for his impressive performance"
    ],
    "Miscellaneous Highlights": [
        "The match was held at the Gabba in Brisbane",
        "The attendance was 22,547, indicating strong interest in the game"
    ],
    "Others": [
        "The article provided detailed over-by-over analysis of the match"
    ]
}