{
    "Relevancy": [
        "Relevant"
    ],
    "New Records": [],
    "Key Match Events": [
        "Jace Jung's 10-pitch walk with Spencer Torkelson at bat leading to a home run",
        "Kenta Maeda's performance after a two-inning opener stint",
        "Jake Rogers' play to help Beau Brieske escape the seventh inning",
        "Beau Brieske's 98.6 mph fastball to end the eighth inning",
        "Jason Foley's 19th save of the season"
    ],
    "Pre-Game Insights": [],
    "Post-Match Reflections": [
        "Spencer Torkelson's comment on keeping the team focused",
        "Manager A.J. Hinch's praise for key plays and bullpen management"
    ],
    "Miscellaneous Highlights": [
        "The Tigers' close proximity to a wild-card spot with 28 games remaining",
        "The team's 10-year playoff drought and recent resurgence"
    ],
    "Others": []
}