{
    "Relevancy": [
        "Relevant"
    ],
    "New Records": [],
    "Key Match Events": [
        "Daniel James missed a penalty, securing Poland's 5-4 win in the penalty shootout",
        "Kieffer Moore smacked his penalty in off the underside of the crossbar",
        "Neco Williams dispatched his penalty into a pocket of the Poland goal"
    ],
    "Pre-Game Insights": [
        "Rob Page admitted it would have been foolish not to practise penalties",
        "Page was adamant that Wales would not have any kind of inferiority complex against a Poland team boasting a household name in Lewandowski"
    ],
    "Post-Match Reflections": [
        "Rob Page gutted as Wales lose Euro 2024 playoff on penalties",
        "It may take Wales a while to get over this defeat"
    ],
    "Miscellaneous Highlights": [
        "Mudryk strikes late as Ukraine defeat Iceland in playoff to reach Euro 2024",
        "Cardiff turns into a theatre of pain and leaves Wales facing an empty summer"
    ],
    "Others": [
        "Chris Mepham picked up his second yellow card but left the field to a hero’s ovation",
        "The Wales supporters sang with increased vigour and a hoarse stadium announcer pleaded for a positive result with added desperation"
    ]
}