{
    "Relevancy": [
        "Relevant"
    ],
    "New Records": [],
    "Key Match Events": [
        "Paul George injured his knee during the game while guarding Jalen Johnson"
    ],
    "Pre-Game Insights": [],
    "Post-Match Reflections": [
        "Nick Nurse expressed hope Paul George would return soon and mentioned Joel Embiid's injury status"
    ],
    "Miscellaneous Highlights": [
        "George's injury occurred in the first half",
        "Joel Embiid is also injured and not playing in pre-season games"
    ],
    "Others": []
}