{
    "Relevancy": [
        "Relevant"
    ],
    "New Records": [
        "Australia became the first team to score over 200 runs in 17 matches so far this tournament"
    ],
    "Key Match Events": [
        "Travis Head and David Warner's 70-run opening partnership",
        "Adam Zampa's 2-28 in four overs",
        "Pat Cummins' disciplined bowling",
        "Liam Livingstone's dropped catch",
        "Moeen Ali's dismissal by David Warner"
    ],
    "Pre-Game Insights": [
        "England had not won against Australia in their last seven T20 matches"
    ],
    "Post-Match Reflections": [
        "Mitch Marsh praised the team's all-round game and the opening partnership",
        "Jos Buttler acknowledged Australia's strong performance and the challenge of coming back from the powerplay",
        "Steven Finn criticized England's performance and said they need to sharpen up"
    ],
    "Miscellaneous Highlights": [
        "The match was played at the historic Kensington Oval in Bridgetown, Barbados",
        "England's chances of defending their title have been dented",
        "Australia plays Namibia next"
    ]
}