{
    "Relevancy": [
        "Relevant"
    ],
    "New Records": [],
    "Key Match Events": [],
    "Pre-Game Insights": [
        "Aiden Markram and Co. would give their all in the final game.",
        "Men in Blue won’t let go of another chance after losing the ODI World Cup 2024 by a whisker.",
        "Both sides have not lost any game in the tournament so far and would strive to become the first-ever undefeated T20 champions."
    ],
    "Post-Match Reflections": [],
    "Miscellaneous Highlights": [],
    "Others": []
}