{
    "Relevancy": [
        "Relevant"
    ],
    "New Records": [],
    "Key Match Events": [
        "The Texas Rangers scored early with two first-inning home runs from Marcus Semien and Nathaniel Lowe.",
        "Andrew Heaney pitched six quality innings.",
        "The Rangers scored two runs in the bottom of the eighth inning due to a Travis Jankowski single and a Los Angeles error."
    ],
    "Pre-Game Insights": [
        "Andrew Heaney emphasized the importance of playing loose and free, particularly when the team is winning.",
        "The Rangers' mindset was focused on setting a foundation for the next season."
    ],
    "Post-Match Reflections": [
        "Marcus Semien and other players were happier and looser due to the team's recent winning streak.",
        "Manager Bruce Bochy noted that the team's performance was their best stretch of the season."
    ],
    "Miscellaneous Highlights": [
        "The Rangers had a 10-3 record in their last 13 games, their best stretch of the season.",
        "They were still trailing the Houston Astros by eight games with 18 to play."
    ],
    "Others": []
}