{
    "Relevancy": [
        "Relevant"
    ],
    "New Records": [
        "Suryakumar Yadav was awarded the Man of the Match",
        "India scored 181 runs in their innings",
        "Afghanistan scored 134 runs in their innings"
    ],
    "Key Match Events": [
        "India won the match by 47 runs",
        "Notable performances by Suryakumar Yadav and Jasprit Bumrah"
    ],
    "Pre-Game Insights": [],
    "Post-Match Reflections": [
        "Quotes from Rohit Sharma and Rashid Khan about the match and their performances"
    ],
    "Miscellaneous Highlights": [
        "The match was played at Kensington Oval, Bridgetown",
        "Match updates and live coverage provided"
    ],
    "Others": []
}