{
    "Relevancy": [
        "Relevant"
    ],
    "New Records": [
        "Ruben Trumpelmann took four wickets, including two in his first two balls.",
        "David Wiese successfully defended a 22-run target in the super over."
    ],
    "Key Match Events": [
        "The match went into a super over after Namibia successfully defended a 22-run target.",
        "Ruben Trumpelmann claimed four wickets, including two quick scalps early in the match."
    ],
    "Pre-Game Insights": [],
    "Post-Match Reflections": [],
    "Miscellaneous Highlights": [
        "Namibia and Oman are both participating in the T20 World Cup for the third time.",
        "The match was played at Kensington Oval in Barbados."
    ],
    "Others": []
}