{
    "Relevancy": [
        "Relevant"
    ],
    "New Records": [],
    "Key Match Events": [],
    "Pre-Game Insights": [
        "Ralf Rangnick's side are now level on points with Slovenia, and both teams are vying to join Norway in the hunt for automatic promotion",
        "Austria have beaten Norway just once in four previous meetings this century",
        "Erling Haaland became his country's highest international scorer",
        "Haaland has averaged 0.94 goals per game for his national side to date",
        "Norway are without their inspirational skipper, Martin Odegaard, and Haaland's Manchester City teammate Oscar Bobb"
    ],
    "Post-Match Reflections": [],
    "Miscellaneous Highlights": [],
    "Others": []
}