{
    "Relevancy": [
        "Relevant"
    ],
    "New Records": [],
    "Key Match Events": [],
    "Pre-Game Insights": [
        "The Los Angeles Dodgers will have Yoshinobu Yamamoto (6-2, 2.63 ERA) start against Antonio Senzatela (0-0, 6.00 ERA) for the Colorado Rockies.",
        "The current betting odds in Australia for the Dodgers vs Rockies game are: Head to Head at $1.26 for the Dodgers and $4.00 for the Rockies, with the Dodgers favored by -1.5 runs at odds of $1.59 and the Rockies +1.5 at $2.45. The over/under for total runs scored is set at 8.5 with odds of $1.91 for both over and under."
    ],
    "Post-Match Reflections": [],
    "Miscellaneous Highlights": [],
    "Others": []
}