{
    "Relevancy": [
        "Relevant"
    ],
    "New Records": [],
    "Key Match Events": [
        "Ben Stokes hit the winning runs",
        "Sam Curran took 4-0-12-3",
        "Afridi left the field through injury",
        "Pakistan lost 8 wickets for 85 runs"
    ],
    "Pre-Game Insights": [
        "England won the toss and chose to bowl first",
        "Predictions or expectations about the match outcome were not explicitly mentioned in the article",
        "Strategies and preparations discussed by teams or players were not explicitly mentioned in the article",
        "Anticipated key player matchups or rivalries were not explicitly mentioned in the article"
    ],
    "Post-Match Reflections": [
        "Jos Buttler expressed pride in the team's resilience after the comeback win",
        "The coach highlighted the victory as a pivotal moment in their playoff push",
        "Ben Stokes was praised for his performance in high-pressure situations"
    ],
    "Miscellaneous Highlights": [
        "The game went into extra innings",
        "Weather or field conditions affecting the match were not mentioned",
        "Historical comparisons or records beyond match performance were not mentioned"
    ],
    "Others": [
        "The article includes various quotes from players and analysts",
        "It mentions the significance of the win for England as the first men's team to be world champions in both ODIs and T20s"
    ]
}