{
    "Relevancy": [
        "Relevant"
    ],
    "New Records": [],
    "Key Match Events": [
        "Equatorial Guinea lost 0-1 to Guinea",
        "Egypt drew 1-1 with DR Congo",
        "Cape Verde won 1-0 against Mauritania",
        "Senegal drew 1-1 with Ivory Coast",
        "Mali won 2-1 against Burkina Faso",
        "Morocco lost 0-2 to South Africa"
    ],
    "Pre-Game Insights": [],
    "Post-Match Reflections": [],
    "Miscellaneous Highlights": [
        "AFCON 2023/2024 Round of 16 Knockout Matches are ongoing",
        "The tournament is being held in Ivory Coast",
        "The knockout stage is a single-elimination style tournament"
    ],
    "Others": [
        "The 2023 Africa Cup of Nations is the 34th edition of the biennial African association football tournament",
        "A total of sixteen teams advanced to the knockout stage"
    ]
}