{
    "Relevancy": [
        "Relevant"
    ],
    "New Records": [
        "Detroit Pistons rank fourth in the Eastern Conference with 11.1 offensive rebounds per game, led by Jalen Duren averaging 3.0.",
        "Cade Cunningham is shooting 44.7% and averaging 24.0 points for the Pistons."
    ],
    "Key Match Events": [],
    "Pre-Game Insights": [
        "Orlando Magic are 20-14 in conference matchups, while Detroit Pistons are 14-18.",
        "The Pistons average 13.5 made 3-pointers per game, 2.1 more than the 11.4 the Magic allow.",
        "Detroit's average points per game is 105.9, 9.3 fewer than Orlando's 115.2."
    ],
    "Post-Match Reflections": [],
    "Miscellaneous Highlights": [
        "The game is scheduled for Wednesday, 7 p.m. EST in Detroit.",
        "Orlando Magic have a 4-6 record in their last 10 games, averaging 101.2 points."
    ],
    "Others": [
        "The article provides injury updates for the Orlando Magic but mentions no injuries for the Detroit Pistons."
    ]
}