{
    "Relevancy": [
        "Relevant"
    ],
    "New Records": [],
    "Key Match Events": [],
    "Pre-Game Insights": [
        "Minnesota Timberwolves finished the previous season with a record of 56-26 overall and 37-15 in Western Conference play. The team averaged 16.9 points off of turnovers, 13.5 second-chance points, and 32.3 bench points.Denver Nuggets finished the previous season with a record of 57-25 overall, 10-6 in Northwest Division games, and 24-17 on the road. The team gave up 109.6 points per game while committing 18.2 fouls."
    ],
    "Post-Match Reflections": [],
    "Miscellaneous Highlights": [],
    "Others": []
}