{
    "Relevancy": [
        "Relevant"
    ],
    "New Records": [],
    "Key Match Events": [
        "Randal Kolo Muani scored the opening goal for France against the run of play in the 30th minute.",
        "Ousmane Dembele scored a stunning second goal for France 12 minutes after the interval."
    ],
    "Pre-Game Insights": [],
    "Post-Match Reflections": [],
    "Miscellaneous Highlights": [],
    "Others": [
        "The match took place on September 9, 2024, at the Parc Olympique Lyonnais in Lyon."
    ]
}