{
    "Relevancy": [
        "Relevant"
    ],
    "New Records": [],
    "Key Match Events": [],
    "Pre-Game Insights": [
        "Stats Insider's predictive analytics model gives the Phillies a 65% chance of beating the Marlins at loanDepot park.",
        "The Phillies (-1.5) are predicted to cover the line 53% of the time, while the 8-run over/under is expected to go over 51% of the time."
    ],
    "Post-Match Reflections": [],
    "Miscellaneous Highlights": [
        "The Marlins are listed as 1.5-run underdogs against the Phillies, with odds of $2.25 available at TAB.",
        "The over/under for total runs scored is set at 8 with TAB, which has odds of $1.91 for the over and $1.91 for the under."
    ],
    "Others": [
        "The game between the Marlins and Phillies at loanDepot park is scheduled to commence at 8:40am AEST on Friday.",
        "The Phillies' starter, Ranger Suárez, has an 11-6 record and a 3.02 ERA."
    ]
}