{
    "Relevancy": [
        "Relevant"
    ],
    "New Records": [
        "Bolivia won 4-0 against Venezuela, the largest margin of victory in this match's history"
    ],
    "Key Match Events": [
        "Bolivia's Vaca scored in the 13th minute",
        "Algaranaz scored a penalty in the 45+5' minute",
        "Terceros scored in the 46' minute",
        "Eduardo Monteiro de Castro Becerra scored in the 89' minute",
        "Cuellar was given a yellow card in the 9' minute",
        "Vaca was given a yellow card in the 14' minute",
        "Eduardo Monteiro de Castro Becerra was given a yellow card in the 90' minute",
        "Casseres Jr scored in the 78' minute",
        "Soteldo scored in the 79' minute"
    ],
    "Pre-Game Insights": [
        "Sports Mole predicted a Venezuela win with a 53.7% probability",
        "The most likely scoreline for a Venezuela win was 0-1 with a 15.72% probability",
        "The likeliest drawn scoreline was 1-1 with a 12.06% probability",
        "The actual scoreline of 4-0 was predicted with a 0.2% likelihood"
    ],
    "Post-Match Reflections": [
        "No quotes or comments from players or coaches are available in the article"
    ],
    "Miscellaneous Highlights": [
        "Bolivia has lost five of their six qualifiers",
        "Venezuela will be targeting maximum points against a nation that has lost five of their six qualifiers",
        "Bolivia has lost their last five matches in World Cup qualifying",
        "Venezuela has not won any of their previous 12 away matches in World Cup qualifying"
    ],
    "Others": [
        "The CONMEBOL World Cup qualifying standings are available in the article",
        "The article includes a form guide for Bolivia and Venezuela"
    ]
}