{
    "Relevancy": [
        "Relevant"
    ],
    "New Records": [],
    "Key Match Events": [],
    "Pre-Game Insights": [
        "Benin have lost their last two games in the fixture",
        "Ranked 91st in the world, the Cheetahs are looking to reach the AFCON showpiece next year for their fifth appearance in history, and a first since 2019",
        "Libya were pegged back by Rwanda in a 1-1 stalemate",
        "Libya have seen a better run than their rivals, who've been going through a rough patch since last year",
        "Prediction: Benin 1-2 Libya"
    ],
    "Post-Match Reflections": [],
    "Miscellaneous Highlights": [],
    "Others": []
}