{
    "Relevancy": [
        "Relevant"
    ],
    "New Records": [],
    "Key Match Events": [
        "Gerardo Arteaga scores the winning goal for Mexico with a left-footed shot from outside the box.",
        "VAR denies Jamaica a goal after Michail Antonio was ruled offside.",
        "Edson Alvarez is substituted due to an injury, impacting Mexico's performance."
    ],
    "Pre-Game Insights": [
        "Mexico and Jamaica are both looking to make an impact in Group B of the Copa America.",
        "NRG Stadium in Houston hosts the match with a 9:00pm ET kick-off."
    ],
    "Post-Match Reflections": [
        "Mexico coach reacts to the win and the injury status of Edson Alvarez.",
        "Jamaica's performance is noted despite the loss, with key players contributing."
    ],
    "Miscellaneous Highlights": [
        "The match is the second game in Group B, following Ecuador's win over Venezuela.",
        "Copa America continues with knockout stages planned for July 14."
    ],
    "Others": [
        "The game is broadcasted on FS1, Univision, and TUDN.",
        "Mexico's participation history in Copa America is noted, with past successes."
    ]
}