{
    "Relevancy": [
        "Relevant"
    ],
    "New Records": [
        "Saiteja Mukkamalla scored 59 runs off 71 balls for USA, finishing not out.",
        "Shayan Jahangir scored 21 runs off 33 balls for USA, contributing to their total of 200 runs."
    ],
    "Key Match Events": [
        "USA won the toss and elected to bat first.",
        "USA's top-order scored 200 runs in 41.3 overs before being dismissed by Namibia.",
        "Namibia's middle-order struggles led to their lower total of 199 runs.",
        "USA won by 6 wickets, securing their victory."
    ],
    "Pre-Game Insights": [
        "USA chose to bat first after winning the toss.",
        "The pitch was expected to be neutral with support for pacers, and the weather was favorable with no rain.",
        "Namibia's Gerhard Erasmus was a key performer in previous matches, while USA's top-order included Smit Patel and Monank Patel."
    ],
    "Post-Match Reflections": [
        "USA secured a win, moving forward in the ICC CWC League 2 ODI standings.",
        "The match highlighted the performance of USA's batting order and Namibia's bowling strength."
    ],
    "Miscellaneous Highlights": [
        "The match was live telecast on Fancode.",
        "Dream11 predictions and tips were provided, with Gerhard Erasmus being a top multiplier choice."
    ],
    "Others": [
        "Namibia and USA were both without injury updates.",
        "The match was part of the ICC CWC League 2 ODI series."
    ]
}