{
    "Relevancy": [
        "Relevant"
    ],
    "New Records": [],
    "Key Match Events": [
        "Trae Young hit a game-winning halfcourt shot",
        "Collin Sexton tied the game with a three-pointer",
        "Lauri Markkanen scored 35 points on 8-15 shooting from three",
        "Clint Capela shot 9-11 from the field and had three blocked shots",
        "Walker Kessler had 21 points, 10 rebounds, and three blocks"
    ],
    "Pre-Game Insights": [
        "Atlanta was on a three-game losing streak",
        "Jalen Johnson was absent for the third time in four games",
        "The Hawks started Vit Krejci in place of Johnson",
        "Utah had a poor defense and was turnover-prone"
    ],
    "Post-Match Reflections": [
        "Trae Young delivered the win despite not playing in the expected manner",
        "The Hawks managed to steal the win without their star player Johnson",
        "This is a big win for the Hawks as they wrap up their road trip"
    ],
    "Miscellaneous Highlights": [
        "The Hawks raced out to a 32-17 lead in the first quarter",
        "Mills and Markkanen both had nine points for the Jazz",
        "Utah started the quarter 1-11 from the field after the Hawks' timeout",
        "Young hit a three to give Atlanta a 93-89 lead in the fourth quarter",
        "Young missed a shot, but Bogdanovic hit a big shot to put Atlanta ahead 113-112"
    ],
    "Others": []
}