{
    "Relevancy": [
        "Relevant"
    ],
    "New Records": [],
    "Key Match Events": [],
    "Pre-Game Insights": [
        "The Czech Republic and Ukraine are both under pressure to deliver a crucial result in their Nations League fixture.",
        "Ivan Hasek's Czech squad has been winless in their last four competitive matches, while Ukraine, under Sergiy Rebrov, are also grappling with inconsistency.",
        "Both teams are recovering from disappointing exits in the Euro 2024 group stages, and the pressure to redeem themselves is palpable."
    ],
    "Post-Match Reflections": [],
    "Miscellaneous Highlights": [],
    "Others": []
}