{
    "Relevancy": [
        "Relevant"
    ],
    "New Records": [
        "Honduras and Jamaica played in the Concacaf Nations League on September 11, 2024, with Jamaica winning 2-0."
    ],
    "Key Match Events": [
        "The match ended with a final score of 2-0 in favor of Jamaica."
    ],
    "Pre-Game Insights": [],
    "Post-Match Reflections": [],
    "Miscellaneous Highlights": [
        "The over/under of 2.5 was exceeded with a total of 3 goals scored."
    ],
    "Others": [
        "The game was covered by Fox Sports with a source link provided."
    ]
}