{
    "Relevancy": [
        "Relevant"
    ],
    "New Records": [
        "2nd-fastest pitch a Tigers player has homered off of in the pitch-tracking era (2008)"
    ],
    "Key Match Events": [
        "Parker Meadows hit a go-ahead grand slam to turn a 3-0 deficit into a 4-3 lead, which ultimately turned into a 4-3 victory"
    ],
    "Pre-Game Insights": [],
    "Post-Match Reflections": [],
    "Miscellaneous Highlights": [
        "Down to their final strike on Thursday, the Detroit Tigers scored four runs in the bottom of the ninth inning to stun the San Diego Padres at Petco Park"
    ],
    "Others": []
}