{
    "Relevancy": [
        "Relevant"
    ],
    "New Records": [],
    "Key Match Events": [
        "Jayson Tatum made a buzzer-beater 3-pointer in overtime to win the game for the Boston Celtics"
    ],
    "Pre-Game Insights": [],
    "Post-Match Reflections": [],
    "Miscellaneous Highlights": [
        "The NBA released a Last Two Minute Report detailing two missed calls on the final possession"
    ],
    "Others": [
        "The article discusses an uncalled travel by Jayson Tatum and a foul that should have been called on Davion Mitchell"
    ]
}